turbo_motor/__init__.py
turbo_motor/model.py
turbo_motor-0.0.3.dist-info/DESCRIPTION.rst
turbo_motor-0.0.3.dist-info/METADATA
turbo_motor-0.0.3.dist-info/RECORD
turbo_motor-0.0.3.dist-info/WHEEL
turbo_motor-0.0.3.dist-info/metadata.json
turbo_motor-0.0.3.dist-info/top_level.txt
