Metadata-Version: 2.0
Name: turbo-motor
Version: 0.0.3
Summary: Turbo motor plugin
Home-page: https://github.com/wecatch/turbo-motor
Author: zhyq0826
Author-email: wecatch.me@gmail.com
License: Apache Software License 2.0
Keywords: turbo_motor,turbo
Platform: UNKNOWN
Classifier: Development Status :: 4 - Beta
Classifier: Intended Audience :: Developers
Classifier: License :: OSI Approved :: Apache Software License
Classifier: Natural Language :: English
Classifier: Programming Language :: Python :: 2
Classifier: Programming Language :: Python :: 2.6
Classifier: Programming Language :: Python :: 2.7
Requires-Dist: Click (>=6.0)
Requires-Dist: motor (==1.1)
Requires-Dist: pymongo (>=3.2)
Requires-Dist: turbo (>=0.4.5)
